reverseshellclient/README.MD
reverseshellclient/__init__.py
reverseshellclient/requirements.txt
reverseshellclient/thirdparty.json
reverseshellclient-0.11.dist-info/LICENSE.rst
reverseshellclient-0.11.dist-info/METADATA
reverseshellclient-0.11.dist-info/WHEEL
reverseshellclient-0.11.dist-info/top_level.txt
reverseshellclient-0.11.dist-info/RECORD
